{
  "performance": [
    {
      "name": "中芯国际(A)",
      "ts_code": "688981.SH",
      "group": "semiconductor",
      "annual_return": -0.0317,
      "max_drawdown": -0.1097,
      "sharpe": -0.19,
      "win_rate": 0.667,
      "profit_factor": 3.85,
      "avg_hold_days": 14.2,
      "total_trades": 6
    },
    {
      "name": "比亚迪(A)",
      "ts_code": "002594.SZ",
      "group": "nev",
      "annual_return": -0.0539,
      "max_drawdown": -0.0403,
      "sharpe": -1.64,
      "win_rate": 0.0,
      "profit_factor": 0.0,
      "avg_hold_days": 13.0,
      "total_trades": 2
    },
    {
      "name": "兆易创新",
      "ts_code": "603986.SH",
      "group": "semiconductor",
      "annual_return": 0.4412,
      "max_drawdown": -0.1654,
      "sharpe": 1.27,
      "win_rate": 0.4,
      "profit_factor": 8.06,
      "avg_hold_days": 20.2,
      "total_trades": 5
    },
    {
      "name": "中芯国际(H)",
      "ts_code": "00981.HK",
      "group": "semiconductor",
      "annual_return": -0.0548,
      "max_drawdown": -0.1267,
      "sharpe": -0.56,
      "win_rate": 0.4,
      "profit_factor": 1.07,
      "avg_hold_days": 14.8,
      "total_trades": 5
    },
    {
      "name": "比亚迪(H)",
      "ts_code": "01211.HK",
      "group": "nev",
      "annual_return": -0.0549,
      "max_drawdown": -0.0458,
      "sharpe": -1.37,
      "win_rate": 0.0,
      "profit_factor": 0.0,
      "avg_hold_days": 19.0,
      "total_trades": 2
    }
  ],
  "equity_curves": [
    {
      "name": "中芯国际(A)",
      "data": [
        {
          "date": "2025-10-09",
          "equity": 100.0
        },
        {
          "date": "2025-10-10",
          "equity": 100.0
        },
        {
          "date": "2025-10-13",
          "equity": 100.0
        },
        {
          "date": "2025-10-14",
          "equity": 100.0
        },
        {
          "date": "2025-10-15",
          "equity": 100.0
        },
        {
          "date": "2025-10-16",
          "equity": 100.0
        },
        {
          "date": "2025-10-17",
          "equity": 100.0
        },
        {
          "date": "2025-10-20",
          "equity": 100.0
        },
        {
          "date": "2025-10-21",
          "equity": 100.0
        },
        {
          "date": "2025-10-22",
          "equity": 100.0
        },
        {
          "date": "2025-10-23",
          "equity": 100.0
        },
        {
          "date": "2025-10-24",
          "equity": 100.0
        },
        {
          "date": "2025-10-27",
          "equity": 100.0
        },
        {
          "date": "2025-10-28",
          "equity": 100.0
        },
        {
          "date": "2025-10-29",
          "equity": 100.0
        },
        {
          "date": "2025-10-30",
          "equity": 100.0
        },
        {
          "date": "2025-10-31",
          "equity": 100.0
        },
        {
          "date": "2025-11-03",
          "equity": 100.0
        },
        {
          "date": "2025-11-04",
          "equity": 100.0
        },
        {
          "date": "2025-11-05",
          "equity": 100.0
        },
        {
          "date": "2025-11-06",
          "equity": 100.0
        },
        {
          "date": "2025-11-07",
          "equity": 100.0
        },
        {
          "date": "2025-11-10",
          "equity": 100.0
        },
        {
          "date": "2025-11-11",
          "equity": 100.0
        },
        {
          "date": "2025-11-12",
          "equity": 100.0
        },
        {
          "date": "2025-11-13",
          "equity": 100.0
        },
        {
          "date": "2025-11-14",
          "equity": 100.0
        },
        {
          "date": "2025-11-17",
          "equity": 100.0
        },
        {
          "date": "2025-11-18",
          "equity": 100.0
        },
        {
          "date": "2025-11-19",
          "equity": 100.0
        },
        {
          "date": "2025-11-20",
          "equity": 100.0
        },
        {
          "date": "2025-11-21",
          "equity": 100.0
        },
        {
          "date": "2025-11-24",
          "equity": 100.0
        },
        {
          "date": "2025-11-25",
          "equity": 100.0
        },
        {
          "date": "2025-11-26",
          "equity": 100.0
        },
        {
          "date": "2025-11-27",
          "equity": 100.0
        },
        {
          "date": "2025-11-28",
          "equity": 100.0
        },
        {
          "date": "2025-12-01",
          "equity": 100.0
        },
        {
          "date": "2025-12-02",
          "equity": 100.0
        },
        {
          "date": "2025-12-03",
          "equity": 100.0
        },
        {
          "date": "2025-12-04",
          "equity": 100.0
        },
        {
          "date": "2025-12-05",
          "equity": 100.0
        },
        {
          "date": "2025-12-08",
          "equity": 100.0
        },
        {
          "date": "2025-12-09",
          "equity": 100.0
        },
        {
          "date": "2025-12-10",
          "equity": 100.0
        },
        {
          "date": "2025-12-11",
          "equity": 100.0
        },
        {
          "date": "2025-12-12",
          "equity": 100.0
        },
        {
          "date": "2025-12-15",
          "equity": 100.0
        },
        {
          "date": "2025-12-16",
          "equity": 100.0
        },
        {
          "date": "2025-12-17",
          "equity": 100.0
        },
        {
          "date": "2025-12-18",
          "equity": 100.0
        },
        {
          "date": "2025-12-19",
          "equity": 100.0
        },
        {
          "date": "2025-12-22",
          "equity": 99.96
        },
        {
          "date": "2025-12-23",
          "equity": 99.83
        },
        {
          "date": "2025-12-24",
          "equity": 100.72
        },
        {
          "date": "2025-12-25",
          "equity": 100.58
        },
        {
          "date": "2025-12-26",
          "equity": 100.18
        },
        {
          "date": "2025-12-29",
          "equity": 100.35
        },
        {
          "date": "2025-12-30",
          "equity": 101.38
        },
        {
          "date": "2025-12-31",
          "equity": 100.09
        },
        {
          "date": "2026-01-05",
          "equity": 103.93
        },
        {
          "date": "2026-01-06",
          "equity": 105.08
        },
        {
          "date": "2026-01-07",
          "equity": 103.94
        },
        {
          "date": "2026-01-08",
          "equity": 104.05
        },
        {
          "date": "2026-01-09",
          "equity": 103.27
        },
        {
          "date": "2026-01-12",
          "equity": 102.53
        },
        {
          "date": "2026-01-13",
          "equity": 100.07
        },
        {
          "date": "2026-01-14",
          "equity": 100.59
        },
        {
          "date": "2026-01-15",
          "equity": 100.56
        },
        {
          "date": "2026-01-16",
          "equity": 102.12
        },
        {
          "date": "2026-01-19",
          "equity": 101.08
        },
        {
          "date": "2026-01-20",
          "equity": 100.83
        },
        {
          "date": "2026-01-21",
          "equity": 100.83
        },
        {
          "date": "2026-01-22",
          "equity": 100.83
        },
        {
          "date": "2026-01-23",
          "equity": 100.83
        },
        {
          "date": "2026-01-26",
          "equity": 100.83
        },
        {
          "date": "2026-01-27",
          "equity": 100.83
        },
        {
          "date": "2026-01-28",
          "equity": 100.83
        },
        {
          "date": "2026-01-29",
          "equity": 100.83
        },
        {
          "date": "2026-01-30",
          "equity": 100.83
        },
        {
          "date": "2026-02-02",
          "equity": 100.83
        },
        {
          "date": "2026-02-03",
          "equity": 100.83
        },
        {
          "date": "2026-02-04",
          "equity": 100.83
        },
        {
          "date": "2026-02-05",
          "equity": 100.83
        },
        {
          "date": "2026-02-06",
          "equity": 100.83
        },
        {
          "date": "2026-02-09",
          "equity": 100.83
        },
        {
          "date": "2026-02-10",
          "equity": 100.83
        },
        {
          "date": "2026-02-11",
          "equity": 100.83
        },
        {
          "date": "2026-02-12",
          "equity": 100.83
        },
        {
          "date": "2026-02-13",
          "equity": 100.83
        },
        {
          "date": "2026-02-24",
          "equity": 100.83
        },
        {
          "date": "2026-02-25",
          "equity": 100.83
        },
        {
          "date": "2026-02-26",
          "equity": 100.83
        },
        {
          "date": "2026-02-27",
          "equity": 100.83
        },
        {
          "date": "2026-03-02",
          "equity": 100.83
        },
        {
          "date": "2026-03-03",
          "equity": 100.83
        },
        {
          "date": "2026-03-04",
          "equity": 100.83
        },
        {
          "date": "2026-03-05",
          "equity": 100.83
        },
        {
          "date": "2026-03-06",
          "equity": 100.83
        },
        {
          "date": "2026-03-09",
          "equity": 100.83
        },
        {
          "date": "2026-03-10",
          "equity": 100.83
        },
        {
          "date": "2026-03-11",
          "equity": 100.83
        },
        {
          "date": "2026-03-12",
          "equity": 100.83
        },
        {
          "date": "2026-03-13",
          "equity": 100.83
        },
        {
          "date": "2026-03-16",
          "equity": 100.83
        },
        {
          "date": "2026-03-17",
          "equity": 100.83
        },
        {
          "date": "2026-03-18",
          "equity": 100.83
        },
        {
          "date": "2026-03-19",
          "equity": 100.83
        },
        {
          "date": "2026-03-20",
          "equity": 100.83
        },
        {
          "date": "2026-03-23",
          "equity": 100.83
        },
        {
          "date": "2026-03-24",
          "equity": 100.83
        },
        {
          "date": "2026-03-25",
          "equity": 100.83
        },
        {
          "date": "2026-03-26",
          "equity": 100.83
        },
        {
          "date": "2026-03-27",
          "equity": 100.83
        },
        {
          "date": "2026-03-30",
          "equity": 100.83
        },
        {
          "date": "2026-03-31",
          "equity": 100.83
        },
        {
          "date": "2026-04-01",
          "equity": 100.83
        },
        {
          "date": "2026-04-02",
          "equity": 100.83
        },
        {
          "date": "2026-04-03",
          "equity": 100.83
        },
        {
          "date": "2026-04-07",
          "equity": 100.83
        },
        {
          "date": "2026-04-08",
          "equity": 100.83
        },
        {
          "date": "2026-04-09",
          "equity": 100.83
        },
        {
          "date": "2026-04-10",
          "equity": 100.83
        },
        {
          "date": "2026-04-13",
          "equity": 100.83
        },
        {
          "date": "2026-04-14",
          "equity": 100.83
        },
        {
          "date": "2026-04-15",
          "equity": 100.83
        },
        {
          "date": "2026-04-16",
          "equity": 100.83
        },
        {
          "date": "2026-04-17",
          "equity": 100.83
        },
        {
          "date": "2026-04-20",
          "equity": 100.98
        },
        {
          "date": "2026-04-21",
          "equity": 100.84
        },
        {
          "date": "2026-04-22",
          "equity": 100.96
        },
        {
          "date": "2026-04-23",
          "equity": 100.41
        },
        {
          "date": "2026-04-24",
          "equity": 101.39
        },
        {
          "date": "2026-04-27",
          "equity": 104.24
        },
        {
          "date": "2026-04-28",
          "equity": 102.69
        },
        {
          "date": "2026-04-29",
          "equity": 101.77
        },
        {
          "date": "2026-04-30",
          "equity": 105.26
        },
        {
          "date": "2026-05-06",
          "equity": 108.12
        },
        {
          "date": "2026-05-07",
          "equity": 109.76
        },
        {
          "date": "2026-05-08",
          "equity": 106.09
        },
        {
          "date": "2026-05-11",
          "equity": 107.7
        },
        {
          "date": "2026-05-12",
          "equity": 107.31
        },
        {
          "date": "2026-05-13",
          "equity": 106.96
        },
        {
          "date": "2026-05-14",
          "equity": 104.27
        },
        {
          "date": "2026-05-15",
          "equity": 105.03
        },
        {
          "date": "2026-05-18",
          "equity": 104.08
        },
        {
          "date": "2026-05-19",
          "equity": 101.74
        },
        {
          "date": "2026-05-20",
          "equity": 101.64
        },
        {
          "date": "2026-05-21",
          "equity": 99.53
        },
        {
          "date": "2026-05-22",
          "equity": 100.84
        },
        {
          "date": "2026-05-25",
          "equity": 109.46
        },
        {
          "date": "2026-05-26",
          "equity": 106.32
        },
        {
          "date": "2026-05-27",
          "equity": 104.96
        },
        {
          "date": "2026-05-28",
          "equity": 108.63
        },
        {
          "date": "2026-05-29",
          "equity": 101.05
        },
        {
          "date": "2026-06-01",
          "equity": 99.6
        },
        {
          "date": "2026-06-02",
          "equity": 99.6
        },
        {
          "date": "2026-06-03",
          "equity": 99.6
        },
        {
          "date": "2026-06-04",
          "equity": 99.6
        },
        {
          "date": "2026-06-05",
          "equity": 99.6
        },
        {
          "date": "2026-06-08",
          "equity": 99.6
        },
        {
          "date": "2026-06-09",
          "equity": 99.6
        },
        {
          "date": "2026-06-10",
          "equity": 99.6
        },
        {
          "date": "2026-06-11",
          "equity": 99.6
        },
        {
          "date": "2026-06-12",
          "equity": 99.6
        },
        {
          "date": "2026-06-15",
          "equity": 99.6
        },
        {
          "date": "2026-06-16",
          "equity": 99.6
        },
        {
          "date": "2026-06-17",
          "equity": 99.6
        },
        {
          "date": "2026-06-18",
          "equity": 99.6
        },
        {
          "date": "2026-06-22",
          "equity": 99.6
        },
        {
          "date": "2026-06-23",
          "equity": 99.6
        },
        {
          "date": "2026-06-24",
          "equity": 99.6
        },
        {
          "date": "2026-06-25",
          "equity": 99.6
        },
        {
          "date": "2026-06-26",
          "equity": 99.6
        },
        {
          "date": "2026-06-29",
          "equity": 99.6
        },
        {
          "date": "2026-06-30",
          "equity": 99.43
        },
        {
          "date": "2026-07-01",
          "equity": 98.95
        },
        {
          "date": "2026-07-02",
          "equity": 97.71
        },
        {
          "date": "2026-07-03",
          "equity": 97.71
        },
        {
          "date": "2026-07-06",
          "equity": 97.71
        },
        {
          "date": "2026-07-06",
          "equity": 97.71
        }
      ]
    },
    {
      "name": "比亚迪(A)",
      "data": [
        {
          "date": "2025-09-23",
          "equity": 100.0
        },
        {
          "date": "2025-09-24",
          "equity": 100.0
        },
        {
          "date": "2025-09-25",
          "equity": 100.0
        },
        {
          "date": "2025-09-26",
          "equity": 100.0
        },
        {
          "date": "2025-09-29",
          "equity": 100.0
        },
        {
          "date": "2025-09-30",
          "equity": 100.0
        },
        {
          "date": "2025-10-09",
          "equity": 100.0
        },
        {
          "date": "2025-10-10",
          "equity": 100.0
        },
        {
          "date": "2025-10-13",
          "equity": 100.0
        },
        {
          "date": "2025-10-14",
          "equity": 100.0
        },
        {
          "date": "2025-10-15",
          "equity": 100.0
        },
        {
          "date": "2025-10-16",
          "equity": 100.0
        },
        {
          "date": "2025-10-17",
          "equity": 100.0
        },
        {
          "date": "2025-10-20",
          "equity": 100.0
        },
        {
          "date": "2025-10-21",
          "equity": 100.0
        },
        {
          "date": "2025-10-22",
          "equity": 100.0
        },
        {
          "date": "2025-10-23",
          "equity": 100.0
        },
        {
          "date": "2025-10-24",
          "equity": 100.0
        },
        {
          "date": "2025-10-27",
          "equity": 100.0
        },
        {
          "date": "2025-10-28",
          "equity": 100.0
        },
        {
          "date": "2025-10-29",
          "equity": 100.0
        },
        {
          "date": "2025-10-30",
          "equity": 100.0
        },
        {
          "date": "2025-10-31",
          "equity": 100.0
        },
        {
          "date": "2025-11-03",
          "equity": 100.0
        },
        {
          "date": "2025-11-04",
          "equity": 100.0
        },
        {
          "date": "2025-11-05",
          "equity": 100.0
        },
        {
          "date": "2025-11-06",
          "equity": 100.0
        },
        {
          "date": "2025-11-07",
          "equity": 100.0
        },
        {
          "date": "2025-11-10",
          "equity": 100.0
        },
        {
          "date": "2025-11-11",
          "equity": 100.0
        },
        {
          "date": "2025-11-12",
          "equity": 100.0
        },
        {
          "date": "2025-11-13",
          "equity": 100.0
        },
        {
          "date": "2025-11-14",
          "equity": 100.0
        },
        {
          "date": "2025-11-17",
          "equity": 100.0
        },
        {
          "date": "2025-11-18",
          "equity": 100.0
        },
        {
          "date": "2025-11-19",
          "equity": 100.0
        },
        {
          "date": "2025-11-20",
          "equity": 100.0
        },
        {
          "date": "2025-11-21",
          "equity": 100.0
        },
        {
          "date": "2025-11-24",
          "equity": 100.0
        },
        {
          "date": "2025-11-25",
          "equity": 100.0
        },
        {
          "date": "2025-11-26",
          "equity": 100.0
        },
        {
          "date": "2025-11-27",
          "equity": 100.0
        },
        {
          "date": "2025-11-28",
          "equity": 100.0
        },
        {
          "date": "2025-12-01",
          "equity": 100.0
        },
        {
          "date": "2025-12-02",
          "equity": 100.0
        },
        {
          "date": "2025-12-03",
          "equity": 100.0
        },
        {
          "date": "2025-12-04",
          "equity": 100.0
        },
        {
          "date": "2025-12-05",
          "equity": 100.0
        },
        {
          "date": "2025-12-08",
          "equity": 100.0
        },
        {
          "date": "2025-12-09",
          "equity": 100.0
        },
        {
          "date": "2025-12-10",
          "equity": 100.0
        },
        {
          "date": "2025-12-11",
          "equity": 100.0
        },
        {
          "date": "2025-12-12",
          "equity": 100.0
        },
        {
          "date": "2025-12-15",
          "equity": 100.0
        },
        {
          "date": "2025-12-16",
          "equity": 100.0
        },
        {
          "date": "2025-12-17",
          "equity": 100.0
        },
        {
          "date": "2025-12-18",
          "equity": 100.0
        },
        {
          "date": "2025-12-19",
          "equity": 100.0
        },
        {
          "date": "2025-12-22",
          "equity": 100.0
        },
        {
          "date": "2025-12-23",
          "equity": 100.0
        },
        {
          "date": "2025-12-24",
          "equity": 100.0
        },
        {
          "date": "2025-12-25",
          "equity": 100.0
        },
        {
          "date": "2025-12-26",
          "equity": 99.69
        },
        {
          "date": "2025-12-29",
          "equity": 99.8
        },
        {
          "date": "2025-12-30",
          "equity": 99.56
        },
        {
          "date": "2025-12-31",
          "equity": 98.5
        },
        {
          "date": "2026-01-05",
          "equity": 98.7
        },
        {
          "date": "2026-01-06",
          "equity": 99.68
        },
        {
          "date": "2026-01-07",
          "equity": 98.44
        },
        {
          "date": "2026-01-08",
          "equity": 98.0
        },
        {
          "date": "2026-01-09",
          "equity": 98.0
        },
        {
          "date": "2026-01-12",
          "equity": 98.0
        },
        {
          "date": "2026-01-13",
          "equity": 98.0
        },
        {
          "date": "2026-01-14",
          "equity": 98.0
        },
        {
          "date": "2026-01-15",
          "equity": 98.0
        },
        {
          "date": "2026-01-16",
          "equity": 98.0
        },
        {
          "date": "2026-01-19",
          "equity": 98.0
        },
        {
          "date": "2026-01-20",
          "equity": 98.0
        },
        {
          "date": "2026-01-21",
          "equity": 98.0
        },
        {
          "date": "2026-01-22",
          "equity": 98.0
        },
        {
          "date": "2026-01-23",
          "equity": 98.0
        },
        {
          "date": "2026-01-26",
          "equity": 98.0
        },
        {
          "date": "2026-01-27",
          "equity": 98.0
        },
        {
          "date": "2026-01-28",
          "equity": 98.0
        },
        {
          "date": "2026-01-29",
          "equity": 98.0
        },
        {
          "date": "2026-01-30",
          "equity": 98.0
        },
        {
          "date": "2026-02-02",
          "equity": 98.0
        },
        {
          "date": "2026-02-03",
          "equity": 98.0
        },
        {
          "date": "2026-02-04",
          "equity": 98.0
        },
        {
          "date": "2026-02-05",
          "equity": 98.0
        },
        {
          "date": "2026-02-06",
          "equity": 98.0
        },
        {
          "date": "2026-02-09",
          "equity": 98.0
        },
        {
          "date": "2026-02-10",
          "equity": 98.0
        },
        {
          "date": "2026-02-11",
          "equity": 98.0
        },
        {
          "date": "2026-02-12",
          "equity": 98.0
        },
        {
          "date": "2026-02-13",
          "equity": 98.0
        },
        {
          "date": "2026-02-24",
          "equity": 98.0
        },
        {
          "date": "2026-02-25",
          "equity": 98.0
        },
        {
          "date": "2026-02-26",
          "equity": 98.0
        },
        {
          "date": "2026-02-27",
          "equity": 98.0
        },
        {
          "date": "2026-03-02",
          "equity": 98.0
        },
        {
          "date": "2026-03-03",
          "equity": 98.0
        },
        {
          "date": "2026-03-04",
          "equity": 98.0
        },
        {
          "date": "2026-03-05",
          "equity": 98.0
        },
        {
          "date": "2026-03-06",
          "equity": 98.0
        },
        {
          "date": "2026-03-09",
          "equity": 98.0
        },
        {
          "date": "2026-03-10",
          "equity": 98.0
        },
        {
          "date": "2026-03-11",
          "equity": 98.0
        },
        {
          "date": "2026-03-12",
          "equity": 98.0
        },
        {
          "date": "2026-03-13",
          "equity": 98.0
        },
        {
          "date": "2026-03-16",
          "equity": 97.96
        },
        {
          "date": "2026-03-17",
          "equity": 97.33
        },
        {
          "date": "2026-03-18",
          "equity": 96.91
        },
        {
          "date": "2026-03-19",
          "equity": 97.13
        },
        {
          "date": "2026-03-20",
          "equity": 97.39
        },
        {
          "date": "2026-03-23",
          "equity": 98.88
        },
        {
          "date": "2026-03-24",
          "equity": 98.33
        },
        {
          "date": "2026-03-25",
          "equity": 98.31
        },
        {
          "date": "2026-03-26",
          "equity": 96.41
        },
        {
          "date": "2026-03-27",
          "equity": 97.6
        },
        {
          "date": "2026-03-30",
          "equity": 98.01
        },
        {
          "date": "2026-03-31",
          "equity": 97.57
        },
        {
          "date": "2026-04-01",
          "equity": 96.14
        },
        {
          "date": "2026-04-02",
          "equity": 95.97
        },
        {
          "date": "2026-04-03",
          "equity": 95.97
        },
        {
          "date": "2026-04-07",
          "equity": 95.97
        },
        {
          "date": "2026-04-08",
          "equity": 95.97
        },
        {
          "date": "2026-04-09",
          "equity": 95.97
        },
        {
          "date": "2026-04-10",
          "equity": 95.97
        },
        {
          "date": "2026-04-13",
          "equity": 95.97
        },
        {
          "date": "2026-04-14",
          "equity": 95.97
        },
        {
          "date": "2026-04-15",
          "equity": 95.97
        },
        {
          "date": "2026-04-16",
          "equity": 95.97
        },
        {
          "date": "2026-04-17",
          "equity": 95.97
        },
        {
          "date": "2026-04-20",
          "equity": 95.97
        },
        {
          "date": "2026-04-21",
          "equity": 95.97
        },
        {
          "date": "2026-04-22",
          "equity": 95.97
        },
        {
          "date": "2026-04-23",
          "equity": 95.97
        },
        {
          "date": "2026-04-24",
          "equity": 95.97
        },
        {
          "date": "2026-04-27",
          "equity": 95.97
        },
        {
          "date": "2026-04-28",
          "equity": 95.97
        },
        {
          "date": "2026-04-29",
          "equity": 95.97
        },
        {
          "date": "2026-04-30",
          "equity": 95.97
        },
        {
          "date": "2026-05-06",
          "equity": 95.97
        },
        {
          "date": "2026-05-07",
          "equity": 95.97
        },
        {
          "date": "2026-05-08",
          "equity": 95.97
        },
        {
          "date": "2026-05-11",
          "equity": 95.97
        },
        {
          "date": "2026-05-12",
          "equity": 95.97
        },
        {
          "date": "2026-05-13",
          "equity": 95.97
        },
        {
          "date": "2026-05-14",
          "equity": 95.97
        },
        {
          "date": "2026-05-15",
          "equity": 95.97
        },
        {
          "date": "2026-05-18",
          "equity": 95.97
        },
        {
          "date": "2026-05-19",
          "equity": 95.97
        },
        {
          "date": "2026-05-20",
          "equity": 95.97
        },
        {
          "date": "2026-05-21",
          "equity": 95.97
        },
        {
          "date": "2026-05-22",
          "equity": 95.97
        },
        {
          "date": "2026-05-25",
          "equity": 95.97
        },
        {
          "date": "2026-05-26",
          "equity": 95.97
        },
        {
          "date": "2026-05-27",
          "equity": 95.97
        },
        {
          "date": "2026-05-28",
          "equity": 95.97
        },
        {
          "date": "2026-05-29",
          "equity": 95.97
        },
        {
          "date": "2026-06-01",
          "equity": 95.97
        },
        {
          "date": "2026-06-02",
          "equity": 95.97
        },
        {
          "date": "2026-06-03",
          "equity": 95.97
        },
        {
          "date": "2026-06-04",
          "equity": 95.97
        },
        {
          "date": "2026-06-05",
          "equity": 95.97
        },
        {
          "date": "2026-06-08",
          "equity": 95.97
        },
        {
          "date": "2026-06-09",
          "equity": 95.97
        },
        {
          "date": "2026-06-10",
          "equity": 95.97
        },
        {
          "date": "2026-06-11",
          "equity": 95.97
        },
        {
          "date": "2026-06-12",
          "equity": 95.97
        },
        {
          "date": "2026-06-15",
          "equity": 95.97
        },
        {
          "date": "2026-06-16",
          "equity": 95.97
        },
        {
          "date": "2026-06-17",
          "equity": 95.97
        },
        {
          "date": "2026-06-18",
          "equity": 95.97
        },
        {
          "date": "2026-06-22",
          "equity": 95.97
        },
        {
          "date": "2026-06-23",
          "equity": 95.97
        },
        {
          "date": "2026-06-24",
          "equity": 95.97
        },
        {
          "date": "2026-06-25",
          "equity": 95.97
        },
        {
          "date": "2026-06-26",
          "equity": 95.97
        },
        {
          "date": "2026-06-29",
          "equity": 95.97
        },
        {
          "date": "2026-06-30",
          "equity": 95.97
        },
        {
          "date": "2026-07-01",
          "equity": 95.97
        },
        {
          "date": "2026-07-02",
          "equity": 95.97
        },
        {
          "date": "2026-07-03",
          "equity": 95.97
        },
        {
          "date": "2026-07-06",
          "equity": 95.97
        },
        {
          "date": "2026-07-06",
          "equity": 95.97
        }
      ]
    },
    {
      "name": "兆易创新",
      "data": [
        {
          "date": "2025-09-23",
          "equity": 100.0
        },
        {
          "date": "2025-09-24",
          "equity": 100.0
        },
        {
          "date": "2025-09-25",
          "equity": 100.0
        },
        {
          "date": "2025-09-26",
          "equity": 100.0
        },
        {
          "date": "2025-09-29",
          "equity": 100.0
        },
        {
          "date": "2025-09-30",
          "equity": 98.57
        },
        {
          "date": "2025-10-09",
          "equity": 100.52
        },
        {
          "date": "2025-10-10",
          "equity": 98.85
        },
        {
          "date": "2025-10-13",
          "equity": 97.7
        },
        {
          "date": "2025-10-14",
          "equity": 96.49
        },
        {
          "date": "2025-10-15",
          "equity": 96.49
        },
        {
          "date": "2025-10-16",
          "equity": 96.49
        },
        {
          "date": "2025-10-17",
          "equity": 96.49
        },
        {
          "date": "2025-10-20",
          "equity": 96.49
        },
        {
          "date": "2025-10-21",
          "equity": 96.49
        },
        {
          "date": "2025-10-22",
          "equity": 96.49
        },
        {
          "date": "2025-10-23",
          "equity": 96.49
        },
        {
          "date": "2025-10-24",
          "equity": 96.49
        },
        {
          "date": "2025-10-27",
          "equity": 96.95
        },
        {
          "date": "2025-10-28",
          "equity": 97.2
        },
        {
          "date": "2025-10-29",
          "equity": 96.5
        },
        {
          "date": "2025-10-30",
          "equity": 95.4
        },
        {
          "date": "2025-10-31",
          "equity": 93.92
        },
        {
          "date": "2025-11-03",
          "equity": 93.92
        },
        {
          "date": "2025-11-04",
          "equity": 93.92
        },
        {
          "date": "2025-11-05",
          "equity": 93.92
        },
        {
          "date": "2025-11-06",
          "equity": 93.92
        },
        {
          "date": "2025-11-07",
          "equity": 93.92
        },
        {
          "date": "2025-11-10",
          "equity": 93.92
        },
        {
          "date": "2025-11-11",
          "equity": 93.92
        },
        {
          "date": "2025-11-12",
          "equity": 93.92
        },
        {
          "date": "2025-11-13",
          "equity": 93.92
        },
        {
          "date": "2025-11-14",
          "equity": 93.92
        },
        {
          "date": "2025-11-17",
          "equity": 93.92
        },
        {
          "date": "2025-11-18",
          "equity": 93.92
        },
        {
          "date": "2025-11-19",
          "equity": 93.92
        },
        {
          "date": "2025-11-20",
          "equity": 93.92
        },
        {
          "date": "2025-11-21",
          "equity": 93.92
        },
        {
          "date": "2025-11-24",
          "equity": 93.92
        },
        {
          "date": "2025-11-25",
          "equity": 93.92
        },
        {
          "date": "2025-11-26",
          "equity": 93.92
        },
        {
          "date": "2025-11-27",
          "equity": 93.92
        },
        {
          "date": "2025-11-28",
          "equity": 93.92
        },
        {
          "date": "2025-12-01",
          "equity": 93.92
        },
        {
          "date": "2025-12-02",
          "equity": 93.92
        },
        {
          "date": "2025-12-03",
          "equity": 93.92
        },
        {
          "date": "2025-12-04",
          "equity": 93.92
        },
        {
          "date": "2025-12-05",
          "equity": 93.92
        },
        {
          "date": "2025-12-08",
          "equity": 93.92
        },
        {
          "date": "2025-12-09",
          "equity": 93.92
        },
        {
          "date": "2025-12-10",
          "equity": 93.92
        },
        {
          "date": "2025-12-11",
          "equity": 93.92
        },
        {
          "date": "2025-12-12",
          "equity": 93.92
        },
        {
          "date": "2025-12-15",
          "equity": 93.92
        },
        {
          "date": "2025-12-16",
          "equity": 93.92
        },
        {
          "date": "2025-12-17",
          "equity": 93.92
        },
        {
          "date": "2025-12-18",
          "equity": 93.92
        },
        {
          "date": "2025-12-19",
          "equity": 93.92
        },
        {
          "date": "2025-12-22",
          "equity": 93.92
        },
        {
          "date": "2025-12-23",
          "equity": 93.92
        },
        {
          "date": "2025-12-24",
          "equity": 93.92
        },
        {
          "date": "2025-12-25",
          "equity": 93.92
        },
        {
          "date": "2025-12-26",
          "equity": 93.92
        },
        {
          "date": "2025-12-29",
          "equity": 93.92
        },
        {
          "date": "2025-12-30",
          "equity": 93.92
        },
        {
          "date": "2025-12-31",
          "equity": 93.92
        },
        {
          "date": "2026-01-05",
          "equity": 93.92
        },
        {
          "date": "2026-01-06",
          "equity": 93.92
        },
        {
          "date": "2026-01-07",
          "equity": 94.15
        },
        {
          "date": "2026-01-08",
          "equity": 93.89
        },
        {
          "date": "2026-01-09",
          "equity": 93.28
        },
        {
          "date": "2026-01-12",
          "equity": 94.1
        },
        {
          "date": "2026-01-13",
          "equity": 94.22
        },
        {
          "date": "2026-01-14",
          "equity": 93.49
        },
        {
          "date": "2026-01-15",
          "equity": 93.62
        },
        {
          "date": "2026-01-16",
          "equity": 95.39
        },
        {
          "date": "2026-01-19",
          "equity": 96.55
        },
        {
          "date": "2026-01-20",
          "equity": 97.02
        },
        {
          "date": "2026-01-21",
          "equity": 99.99
        },
        {
          "date": "2026-01-22",
          "equity": 98.82
        },
        {
          "date": "2026-01-23",
          "equity": 98.02
        },
        {
          "date": "2026-01-26",
          "equity": 97.14
        },
        {
          "date": "2026-01-27",
          "equity": 99.92
        },
        {
          "date": "2026-01-28",
          "equity": 103.03
        },
        {
          "date": "2026-01-29",
          "equity": 99.96
        },
        {
          "date": "2026-01-30",
          "equity": 101.36
        },
        {
          "date": "2026-02-02",
          "equity": 95.39
        },
        {
          "date": "2026-02-03",
          "equity": 97.13
        },
        {
          "date": "2026-02-04",
          "equity": 95.19
        },
        {
          "date": "2026-02-05",
          "equity": 92.52
        },
        {
          "date": "2026-02-06",
          "equity": 92.52
        },
        {
          "date": "2026-02-09",
          "equity": 92.52
        },
        {
          "date": "2026-02-10",
          "equity": 92.52
        },
        {
          "date": "2026-02-11",
          "equity": 92.52
        },
        {
          "date": "2026-02-12",
          "equity": 92.52
        },
        {
          "date": "2026-02-13",
          "equity": 92.52
        },
        {
          "date": "2026-02-24",
          "equity": 92.52
        },
        {
          "date": "2026-02-25",
          "equity": 92.52
        },
        {
          "date": "2026-02-26",
          "equity": 92.52
        },
        {
          "date": "2026-02-27",
          "equity": 92.52
        },
        {
          "date": "2026-03-02",
          "equity": 92.52
        },
        {
          "date": "2026-03-03",
          "equity": 92.52
        },
        {
          "date": "2026-03-04",
          "equity": 92.52
        },
        {
          "date": "2026-03-05",
          "equity": 92.52
        },
        {
          "date": "2026-03-06",
          "equity": 92.52
        },
        {
          "date": "2026-03-09",
          "equity": 92.52
        },
        {
          "date": "2026-03-10",
          "equity": 92.52
        },
        {
          "date": "2026-03-11",
          "equity": 92.52
        },
        {
          "date": "2026-03-12",
          "equity": 92.52
        },
        {
          "date": "2026-03-13",
          "equity": 92.52
        },
        {
          "date": "2026-03-16",
          "equity": 92.52
        },
        {
          "date": "2026-03-17",
          "equity": 92.52
        },
        {
          "date": "2026-03-18",
          "equity": 92.52
        },
        {
          "date": "2026-03-19",
          "equity": 92.52
        },
        {
          "date": "2026-03-20",
          "equity": 92.52
        },
        {
          "date": "2026-03-23",
          "equity": 92.52
        },
        {
          "date": "2026-03-24",
          "equity": 92.52
        },
        {
          "date": "2026-03-25",
          "equity": 92.52
        },
        {
          "date": "2026-03-26",
          "equity": 92.52
        },
        {
          "date": "2026-03-27",
          "equity": 92.52
        },
        {
          "date": "2026-03-30",
          "equity": 92.52
        },
        {
          "date": "2026-03-31",
          "equity": 92.52
        },
        {
          "date": "2026-04-01",
          "equity": 92.52
        },
        {
          "date": "2026-04-02",
          "equity": 92.52
        },
        {
          "date": "2026-04-03",
          "equity": 92.52
        },
        {
          "date": "2026-04-07",
          "equity": 92.52
        },
        {
          "date": "2026-04-08",
          "equity": 92.52
        },
        {
          "date": "2026-04-09",
          "equity": 92.52
        },
        {
          "date": "2026-04-10",
          "equity": 92.52
        },
        {
          "date": "2026-04-13",
          "equity": 92.52
        },
        {
          "date": "2026-04-14",
          "equity": 92.52
        },
        {
          "date": "2026-04-15",
          "equity": 92.52
        },
        {
          "date": "2026-04-16",
          "equity": 92.52
        },
        {
          "date": "2026-04-17",
          "equity": 92.52
        },
        {
          "date": "2026-04-20",
          "equity": 92.52
        },
        {
          "date": "2026-04-21",
          "equity": 92.52
        },
        {
          "date": "2026-04-22",
          "equity": 92.52
        },
        {
          "date": "2026-04-23",
          "equity": 92.52
        },
        {
          "date": "2026-04-24",
          "equity": 92.52
        },
        {
          "date": "2026-04-27",
          "equity": 92.52
        },
        {
          "date": "2026-04-28",
          "equity": 92.52
        },
        {
          "date": "2026-04-29",
          "equity": 92.52
        },
        {
          "date": "2026-04-30",
          "equity": 92.52
        },
        {
          "date": "2026-05-06",
          "equity": 92.37
        },
        {
          "date": "2026-05-07",
          "equity": 92.66
        },
        {
          "date": "2026-05-08",
          "equity": 91.86
        },
        {
          "date": "2026-05-11",
          "equity": 93.25
        },
        {
          "date": "2026-05-12",
          "equity": 92.48
        },
        {
          "date": "2026-05-13",
          "equity": 93.51
        },
        {
          "date": "2026-05-14",
          "equity": 92.71
        },
        {
          "date": "2026-05-15",
          "equity": 93.43
        },
        {
          "date": "2026-05-18",
          "equity": 96.38
        },
        {
          "date": "2026-05-19",
          "equity": 96.93
        },
        {
          "date": "2026-05-20",
          "equity": 101.77
        },
        {
          "date": "2026-05-21",
          "equity": 99.93
        },
        {
          "date": "2026-05-22",
          "equity": 105.08
        },
        {
          "date": "2026-05-25",
          "equity": 111.63
        },
        {
          "date": "2026-05-26",
          "equity": 113.23
        },
        {
          "date": "2026-05-27",
          "equity": 111.54
        },
        {
          "date": "2026-05-28",
          "equity": 107.17
        },
        {
          "date": "2026-05-29",
          "equity": 104.94
        },
        {
          "date": "2026-06-01",
          "equity": 105.07
        },
        {
          "date": "2026-06-02",
          "equity": 106.01
        },
        {
          "date": "2026-06-03",
          "equity": 108.47
        },
        {
          "date": "2026-06-04",
          "equity": 113.66
        },
        {
          "date": "2026-06-05",
          "equity": 107.87
        },
        {
          "date": "2026-06-08",
          "equity": 105.92
        },
        {
          "date": "2026-06-09",
          "equity": 109.62
        },
        {
          "date": "2026-06-10",
          "equity": 106.87
        },
        {
          "date": "2026-06-11",
          "equity": 107.24
        },
        {
          "date": "2026-06-12",
          "equity": 106.96
        },
        {
          "date": "2026-06-15",
          "equity": 112.07
        },
        {
          "date": "2026-06-16",
          "equity": 114.14
        },
        {
          "date": "2026-06-17",
          "equity": 121.6
        },
        {
          "date": "2026-06-18",
          "equity": 127.61
        },
        {
          "date": "2026-06-22",
          "equity": 136.11
        },
        {
          "date": "2026-06-23",
          "equity": 129.29
        },
        {
          "date": "2026-06-24",
          "equity": 138.27
        },
        {
          "date": "2026-06-25",
          "equity": 148.08
        },
        {
          "date": "2026-06-26",
          "equity": 147.35
        },
        {
          "date": "2026-06-29",
          "equity": 157.15
        },
        {
          "date": "2026-06-30",
          "equity": 153.65
        },
        {
          "date": "2026-07-01",
          "equity": 147.64
        },
        {
          "date": "2026-07-02",
          "equity": 136.83
        },
        {
          "date": "2026-07-03",
          "equity": 134.44
        },
        {
          "date": "2026-07-06",
          "equity": 131.16
        },
        {
          "date": "2026-07-06",
          "equity": 131.16
        }
      ]
    },
    {
      "name": "中芯国际(H)",
      "data": [
        {
          "date": "2025-09-23",
          "equity": 100.0
        },
        {
          "date": "2025-09-24",
          "equity": 99.76
        },
        {
          "date": "2025-09-25",
          "equity": 99.79
        },
        {
          "date": "2025-09-26",
          "equity": 98.05
        },
        {
          "date": "2025-09-29",
          "equity": 99.65
        },
        {
          "date": "2025-09-30",
          "equity": 100.85
        },
        {
          "date": "2025-10-02",
          "equity": 107.8
        },
        {
          "date": "2025-10-03",
          "equity": 108.87
        },
        {
          "date": "2025-10-06",
          "equity": 108.99
        },
        {
          "date": "2025-10-08",
          "equity": 107.68
        },
        {
          "date": "2025-10-09",
          "equity": 102.58
        },
        {
          "date": "2025-10-10",
          "equity": 101.55
        },
        {
          "date": "2025-10-13",
          "equity": 101.55
        },
        {
          "date": "2025-10-14",
          "equity": 101.55
        },
        {
          "date": "2025-10-15",
          "equity": 101.55
        },
        {
          "date": "2025-10-16",
          "equity": 101.55
        },
        {
          "date": "2025-10-17",
          "equity": 101.55
        },
        {
          "date": "2025-10-20",
          "equity": 101.55
        },
        {
          "date": "2025-10-21",
          "equity": 101.55
        },
        {
          "date": "2025-10-22",
          "equity": 101.55
        },
        {
          "date": "2025-10-23",
          "equity": 101.55
        },
        {
          "date": "2025-10-24",
          "equity": 101.55
        },
        {
          "date": "2025-10-27",
          "equity": 101.55
        },
        {
          "date": "2025-10-28",
          "equity": 101.55
        },
        {
          "date": "2025-10-30",
          "equity": 101.55
        },
        {
          "date": "2025-10-31",
          "equity": 101.55
        },
        {
          "date": "2025-11-03",
          "equity": 101.55
        },
        {
          "date": "2025-11-04",
          "equity": 101.55
        },
        {
          "date": "2025-11-05",
          "equity": 101.55
        },
        {
          "date": "2025-11-06",
          "equity": 101.55
        },
        {
          "date": "2025-11-07",
          "equity": 101.55
        },
        {
          "date": "2025-11-10",
          "equity": 101.55
        },
        {
          "date": "2025-11-11",
          "equity": 101.55
        },
        {
          "date": "2025-11-12",
          "equity": 101.55
        },
        {
          "date": "2025-11-13",
          "equity": 101.55
        },
        {
          "date": "2025-11-14",
          "equity": 101.55
        },
        {
          "date": "2025-11-17",
          "equity": 101.55
        },
        {
          "date": "2025-11-18",
          "equity": 101.55
        },
        {
          "date": "2025-11-19",
          "equity": 101.55
        },
        {
          "date": "2025-11-20",
          "equity": 101.55
        },
        {
          "date": "2025-11-21",
          "equity": 101.55
        },
        {
          "date": "2025-11-24",
          "equity": 101.55
        },
        {
          "date": "2025-11-25",
          "equity": 101.55
        },
        {
          "date": "2025-11-26",
          "equity": 101.55
        },
        {
          "date": "2025-11-27",
          "equity": 101.55
        },
        {
          "date": "2025-11-28",
          "equity": 101.55
        },
        {
          "date": "2025-12-01",
          "equity": 101.55
        },
        {
          "date": "2025-12-02",
          "equity": 101.55
        },
        {
          "date": "2025-12-03",
          "equity": 101.55
        },
        {
          "date": "2025-12-04",
          "equity": 101.55
        },
        {
          "date": "2025-12-05",
          "equity": 101.55
        },
        {
          "date": "2025-12-08",
          "equity": 101.55
        },
        {
          "date": "2025-12-09",
          "equity": 101.55
        },
        {
          "date": "2025-12-10",
          "equity": 101.55
        },
        {
          "date": "2025-12-11",
          "equity": 101.55
        },
        {
          "date": "2025-12-12",
          "equity": 101.55
        },
        {
          "date": "2025-12-15",
          "equity": 101.55
        },
        {
          "date": "2025-12-16",
          "equity": 101.55
        },
        {
          "date": "2025-12-17",
          "equity": 101.55
        },
        {
          "date": "2025-12-18",
          "equity": 101.55
        },
        {
          "date": "2025-12-19",
          "equity": 101.55
        },
        {
          "date": "2025-12-22",
          "equity": 101.55
        },
        {
          "date": "2025-12-23",
          "equity": 101.55
        },
        {
          "date": "2025-12-24",
          "equity": 101.55
        },
        {
          "date": "2025-12-29",
          "equity": 101.55
        },
        {
          "date": "2025-12-30",
          "equity": 101.55
        },
        {
          "date": "2025-12-31",
          "equity": 101.55
        },
        {
          "date": "2026-01-02",
          "equity": 101.32
        },
        {
          "date": "2026-01-05",
          "equity": 101.74
        },
        {
          "date": "2026-01-06",
          "equity": 101.47
        },
        {
          "date": "2026-01-07",
          "equity": 101.2
        },
        {
          "date": "2026-01-08",
          "equity": 101.27
        },
        {
          "date": "2026-01-09",
          "equity": 101.11
        },
        {
          "date": "2026-01-12",
          "equity": 101.38
        },
        {
          "date": "2026-01-13",
          "equity": 101.12
        },
        {
          "date": "2026-01-14",
          "equity": 101.57
        },
        {
          "date": "2026-01-15",
          "equity": 101.99
        },
        {
          "date": "2026-01-16",
          "equity": 102.53
        },
        {
          "date": "2026-01-19",
          "equity": 101.43
        },
        {
          "date": "2026-01-20",
          "equity": 100.18
        },
        {
          "date": "2026-01-21",
          "equity": 101.56
        },
        {
          "date": "2026-01-22",
          "equity": 101.86
        },
        {
          "date": "2026-01-23",
          "equity": 101.98
        },
        {
          "date": "2026-01-26",
          "equity": 100.71
        },
        {
          "date": "2026-01-27",
          "equity": 101.23
        },
        {
          "date": "2026-01-28",
          "equity": 102.58
        },
        {
          "date": "2026-01-29",
          "equity": 101.56
        },
        {
          "date": "2026-01-30",
          "equity": 100.63
        },
        {
          "date": "2026-02-02",
          "equity": 99.41
        },
        {
          "date": "2026-02-03",
          "equity": 99.41
        },
        {
          "date": "2026-02-04",
          "equity": 99.41
        },
        {
          "date": "2026-02-05",
          "equity": 99.41
        },
        {
          "date": "2026-02-06",
          "equity": 99.41
        },
        {
          "date": "2026-02-09",
          "equity": 99.41
        },
        {
          "date": "2026-02-10",
          "equity": 99.41
        },
        {
          "date": "2026-02-11",
          "equity": 99.41
        },
        {
          "date": "2026-02-12",
          "equity": 99.41
        },
        {
          "date": "2026-02-13",
          "equity": 99.41
        },
        {
          "date": "2026-02-16",
          "equity": 99.41
        },
        {
          "date": "2026-02-20",
          "equity": 99.41
        },
        {
          "date": "2026-02-23",
          "equity": 99.41
        },
        {
          "date": "2026-02-24",
          "equity": 99.41
        },
        {
          "date": "2026-02-25",
          "equity": 99.41
        },
        {
          "date": "2026-02-26",
          "equity": 99.41
        },
        {
          "date": "2026-02-27",
          "equity": 99.41
        },
        {
          "date": "2026-03-02",
          "equity": 99.41
        },
        {
          "date": "2026-03-03",
          "equity": 99.41
        },
        {
          "date": "2026-03-04",
          "equity": 99.41
        },
        {
          "date": "2026-03-05",
          "equity": 99.41
        },
        {
          "date": "2026-03-06",
          "equity": 99.41
        },
        {
          "date": "2026-03-09",
          "equity": 99.41
        },
        {
          "date": "2026-03-10",
          "equity": 99.41
        },
        {
          "date": "2026-03-11",
          "equity": 99.41
        },
        {
          "date": "2026-03-12",
          "equity": 99.41
        },
        {
          "date": "2026-03-13",
          "equity": 99.41
        },
        {
          "date": "2026-03-16",
          "equity": 99.41
        },
        {
          "date": "2026-03-17",
          "equity": 99.41
        },
        {
          "date": "2026-03-18",
          "equity": 99.41
        },
        {
          "date": "2026-03-19",
          "equity": 99.41
        },
        {
          "date": "2026-03-20",
          "equity": 99.41
        },
        {
          "date": "2026-03-23",
          "equity": 99.41
        },
        {
          "date": "2026-03-24",
          "equity": 99.41
        },
        {
          "date": "2026-03-25",
          "equity": 99.41
        },
        {
          "date": "2026-03-26",
          "equity": 99.41
        },
        {
          "date": "2026-03-27",
          "equity": 99.41
        },
        {
          "date": "2026-03-30",
          "equity": 99.41
        },
        {
          "date": "2026-03-31",
          "equity": 99.41
        },
        {
          "date": "2026-04-01",
          "equity": 99.41
        },
        {
          "date": "2026-04-02",
          "equity": 99.41
        },
        {
          "date": "2026-04-08",
          "equity": 99.41
        },
        {
          "date": "2026-04-09",
          "equity": 99.41
        },
        {
          "date": "2026-04-10",
          "equity": 99.41
        },
        {
          "date": "2026-04-13",
          "equity": 99.41
        },
        {
          "date": "2026-04-14",
          "equity": 99.41
        },
        {
          "date": "2026-04-15",
          "equity": 99.41
        },
        {
          "date": "2026-04-16",
          "equity": 99.41
        },
        {
          "date": "2026-04-17",
          "equity": 99.41
        },
        {
          "date": "2026-04-20",
          "equity": 99.41
        },
        {
          "date": "2026-04-21",
          "equity": 99.41
        },
        {
          "date": "2026-04-22",
          "equity": 99.41
        },
        {
          "date": "2026-04-23",
          "equity": 99.41
        },
        {
          "date": "2026-04-24",
          "equity": 99.41
        },
        {
          "date": "2026-04-27",
          "equity": 99.41
        },
        {
          "date": "2026-04-28",
          "equity": 99.41
        },
        {
          "date": "2026-04-29",
          "equity": 99.41
        },
        {
          "date": "2026-04-30",
          "equity": 99.41
        },
        {
          "date": "2026-05-04",
          "equity": 99.64
        },
        {
          "date": "2026-05-05",
          "equity": 99.24
        },
        {
          "date": "2026-05-06",
          "equity": 100.1
        },
        {
          "date": "2026-05-07",
          "equity": 101.05
        },
        {
          "date": "2026-05-08",
          "equity": 99.35
        },
        {
          "date": "2026-05-11",
          "equity": 100.97
        },
        {
          "date": "2026-05-12",
          "equity": 100.97
        },
        {
          "date": "2026-05-13",
          "equity": 99.75
        },
        {
          "date": "2026-05-14",
          "equity": 98.42
        },
        {
          "date": "2026-05-15",
          "equity": 98.25
        },
        {
          "date": "2026-05-18",
          "equity": 97.59
        },
        {
          "date": "2026-05-19",
          "equity": 97.59
        },
        {
          "date": "2026-05-20",
          "equity": 97.59
        },
        {
          "date": "2026-05-21",
          "equity": 97.59
        },
        {
          "date": "2026-05-22",
          "equity": 95.18
        },
        {
          "date": "2026-05-26",
          "equity": 96.09
        },
        {
          "date": "2026-05-27",
          "equity": 96.25
        },
        {
          "date": "2026-05-28",
          "equity": 96.86
        },
        {
          "date": "2026-05-29",
          "equity": 95.84
        },
        {
          "date": "2026-06-01",
          "equity": 95.84
        },
        {
          "date": "2026-06-02",
          "equity": 95.84
        },
        {
          "date": "2026-06-03",
          "equity": 95.84
        },
        {
          "date": "2026-06-04",
          "equity": 95.84
        },
        {
          "date": "2026-06-05",
          "equity": 95.84
        },
        {
          "date": "2026-06-08",
          "equity": 95.84
        },
        {
          "date": "2026-06-09",
          "equity": 95.84
        },
        {
          "date": "2026-06-10",
          "equity": 95.84
        },
        {
          "date": "2026-06-11",
          "equity": 95.84
        },
        {
          "date": "2026-06-12",
          "equity": 95.84
        },
        {
          "date": "2026-06-15",
          "equity": 95.84
        },
        {
          "date": "2026-06-16",
          "equity": 95.84
        },
        {
          "date": "2026-06-17",
          "equity": 95.84
        },
        {
          "date": "2026-06-18",
          "equity": 95.84
        },
        {
          "date": "2026-06-22",
          "equity": 95.84
        },
        {
          "date": "2026-06-23",
          "equity": 95.84
        },
        {
          "date": "2026-06-24",
          "equity": 95.84
        },
        {
          "date": "2026-06-25",
          "equity": 95.84
        },
        {
          "date": "2026-06-26",
          "equity": 95.84
        },
        {
          "date": "2026-06-29",
          "equity": 95.84
        },
        {
          "date": "2026-06-30",
          "equity": 95.84
        },
        {
          "date": "2026-07-02",
          "equity": 95.84
        },
        {
          "date": "2026-07-03",
          "equity": 95.84
        },
        {
          "date": "2026-07-06",
          "equity": 95.84
        },
        {
          "date": "2026-07-06",
          "equity": 95.84
        }
      ]
    },
    {
      "name": "比亚迪(H)",
      "data": [
        {
          "date": "2025-09-23",
          "equity": 100.0
        },
        {
          "date": "2025-09-24",
          "equity": 100.0
        },
        {
          "date": "2025-09-25",
          "equity": 100.0
        },
        {
          "date": "2025-09-26",
          "equity": 100.0
        },
        {
          "date": "2025-09-29",
          "equity": 100.0
        },
        {
          "date": "2025-09-30",
          "equity": 100.0
        },
        {
          "date": "2025-10-02",
          "equity": 100.0
        },
        {
          "date": "2025-10-03",
          "equity": 100.0
        },
        {
          "date": "2025-10-06",
          "equity": 100.0
        },
        {
          "date": "2025-10-08",
          "equity": 100.0
        },
        {
          "date": "2025-10-09",
          "equity": 100.0
        },
        {
          "date": "2025-10-10",
          "equity": 100.0
        },
        {
          "date": "2025-10-13",
          "equity": 100.0
        },
        {
          "date": "2025-10-14",
          "equity": 100.0
        },
        {
          "date": "2025-10-15",
          "equity": 100.0
        },
        {
          "date": "2025-10-16",
          "equity": 100.0
        },
        {
          "date": "2025-10-17",
          "equity": 100.0
        },
        {
          "date": "2025-10-20",
          "equity": 100.0
        },
        {
          "date": "2025-10-21",
          "equity": 100.0
        },
        {
          "date": "2025-10-22",
          "equity": 100.0
        },
        {
          "date": "2025-10-23",
          "equity": 100.0
        },
        {
          "date": "2025-10-24",
          "equity": 100.0
        },
        {
          "date": "2025-10-27",
          "equity": 100.0
        },
        {
          "date": "2025-10-28",
          "equity": 100.0
        },
        {
          "date": "2025-10-30",
          "equity": 100.0
        },
        {
          "date": "2025-10-31",
          "equity": 100.0
        },
        {
          "date": "2025-11-03",
          "equity": 100.0
        },
        {
          "date": "2025-11-04",
          "equity": 100.0
        },
        {
          "date": "2025-11-05",
          "equity": 100.0
        },
        {
          "date": "2025-11-06",
          "equity": 100.0
        },
        {
          "date": "2025-11-07",
          "equity": 100.0
        },
        {
          "date": "2025-11-10",
          "equity": 100.0
        },
        {
          "date": "2025-11-11",
          "equity": 100.0
        },
        {
          "date": "2025-11-12",
          "equity": 100.0
        },
        {
          "date": "2025-11-13",
          "equity": 100.0
        },
        {
          "date": "2025-11-14",
          "equity": 100.0
        },
        {
          "date": "2025-11-17",
          "equity": 100.0
        },
        {
          "date": "2025-11-18",
          "equity": 100.0
        },
        {
          "date": "2025-11-19",
          "equity": 100.0
        },
        {
          "date": "2025-11-20",
          "equity": 100.0
        },
        {
          "date": "2025-11-21",
          "equity": 100.0
        },
        {
          "date": "2025-11-24",
          "equity": 100.0
        },
        {
          "date": "2025-11-25",
          "equity": 100.0
        },
        {
          "date": "2025-11-26",
          "equity": 100.0
        },
        {
          "date": "2025-11-27",
          "equity": 100.0
        },
        {
          "date": "2025-11-28",
          "equity": 100.0
        },
        {
          "date": "2025-12-01",
          "equity": 100.0
        },
        {
          "date": "2025-12-02",
          "equity": 100.0
        },
        {
          "date": "2025-12-03",
          "equity": 100.0
        },
        {
          "date": "2025-12-04",
          "equity": 100.0
        },
        {
          "date": "2025-12-05",
          "equity": 100.0
        },
        {
          "date": "2025-12-08",
          "equity": 100.0
        },
        {
          "date": "2025-12-09",
          "equity": 100.0
        },
        {
          "date": "2025-12-10",
          "equity": 100.0
        },
        {
          "date": "2025-12-11",
          "equity": 100.0
        },
        {
          "date": "2025-12-12",
          "equity": 100.0
        },
        {
          "date": "2025-12-15",
          "equity": 100.0
        },
        {
          "date": "2025-12-16",
          "equity": 100.0
        },
        {
          "date": "2025-12-17",
          "equity": 100.0
        },
        {
          "date": "2025-12-18",
          "equity": 100.0
        },
        {
          "date": "2025-12-19",
          "equity": 100.0
        },
        {
          "date": "2025-12-22",
          "equity": 100.0
        },
        {
          "date": "2025-12-23",
          "equity": 100.0
        },
        {
          "date": "2025-12-24",
          "equity": 100.0
        },
        {
          "date": "2025-12-29",
          "equity": 100.0
        },
        {
          "date": "2025-12-30",
          "equity": 100.0
        },
        {
          "date": "2025-12-31",
          "equity": 100.0
        },
        {
          "date": "2026-01-02",
          "equity": 100.0
        },
        {
          "date": "2026-01-05",
          "equity": 100.0
        },
        {
          "date": "2026-01-06",
          "equity": 100.0
        },
        {
          "date": "2026-01-07",
          "equity": 100.0
        },
        {
          "date": "2026-01-08",
          "equity": 100.0
        },
        {
          "date": "2026-01-09",
          "equity": 100.0
        },
        {
          "date": "2026-01-12",
          "equity": 100.0
        },
        {
          "date": "2026-01-13",
          "equity": 100.0
        },
        {
          "date": "2026-01-14",
          "equity": 100.0
        },
        {
          "date": "2026-01-15",
          "equity": 100.0
        },
        {
          "date": "2026-01-16",
          "equity": 100.0
        },
        {
          "date": "2026-01-19",
          "equity": 100.0
        },
        {
          "date": "2026-01-20",
          "equity": 100.0
        },
        {
          "date": "2026-01-21",
          "equity": 100.0
        },
        {
          "date": "2026-01-22",
          "equity": 100.0
        },
        {
          "date": "2026-01-23",
          "equity": 100.0
        },
        {
          "date": "2026-01-26",
          "equity": 100.0
        },
        {
          "date": "2026-01-27",
          "equity": 100.0
        },
        {
          "date": "2026-01-28",
          "equity": 99.89
        },
        {
          "date": "2026-01-29",
          "equity": 99.55
        },
        {
          "date": "2026-01-30",
          "equity": 98.04
        },
        {
          "date": "2026-02-02",
          "equity": 98.04
        },
        {
          "date": "2026-02-03",
          "equity": 98.04
        },
        {
          "date": "2026-02-04",
          "equity": 98.04
        },
        {
          "date": "2026-02-05",
          "equity": 98.04
        },
        {
          "date": "2026-02-06",
          "equity": 98.04
        },
        {
          "date": "2026-02-09",
          "equity": 98.04
        },
        {
          "date": "2026-02-10",
          "equity": 98.04
        },
        {
          "date": "2026-02-11",
          "equity": 98.04
        },
        {
          "date": "2026-02-12",
          "equity": 98.04
        },
        {
          "date": "2026-02-13",
          "equity": 98.04
        },
        {
          "date": "2026-02-16",
          "equity": 98.04
        },
        {
          "date": "2026-02-20",
          "equity": 98.04
        },
        {
          "date": "2026-02-23",
          "equity": 98.04
        },
        {
          "date": "2026-02-24",
          "equity": 98.04
        },
        {
          "date": "2026-02-25",
          "equity": 98.04
        },
        {
          "date": "2026-02-26",
          "equity": 98.04
        },
        {
          "date": "2026-02-27",
          "equity": 98.04
        },
        {
          "date": "2026-03-02",
          "equity": 98.04
        },
        {
          "date": "2026-03-03",
          "equity": 98.04
        },
        {
          "date": "2026-03-04",
          "equity": 98.04
        },
        {
          "date": "2026-03-05",
          "equity": 98.04
        },
        {
          "date": "2026-03-06",
          "equity": 98.04
        },
        {
          "date": "2026-03-09",
          "equity": 98.04
        },
        {
          "date": "2026-03-10",
          "equity": 98.04
        },
        {
          "date": "2026-03-11",
          "equity": 98.04
        },
        {
          "date": "2026-03-12",
          "equity": 98.04
        },
        {
          "date": "2026-03-13",
          "equity": 98.04
        },
        {
          "date": "2026-03-16",
          "equity": 97.79
        },
        {
          "date": "2026-03-17",
          "equity": 97.84
        },
        {
          "date": "2026-03-18",
          "equity": 97.27
        },
        {
          "date": "2026-03-19",
          "equity": 97.52
        },
        {
          "date": "2026-03-20",
          "equity": 97.66
        },
        {
          "date": "2026-03-23",
          "equity": 97.32
        },
        {
          "date": "2026-03-24",
          "equity": 98.46
        },
        {
          "date": "2026-03-25",
          "equity": 98.31
        },
        {
          "date": "2026-03-26",
          "equity": 97.39
        },
        {
          "date": "2026-03-27",
          "equity": 98.34
        },
        {
          "date": "2026-03-30",
          "equity": 98.16
        },
        {
          "date": "2026-03-31",
          "equity": 98.16
        },
        {
          "date": "2026-04-01",
          "equity": 97.89
        },
        {
          "date": "2026-04-02",
          "equity": 97.69
        },
        {
          "date": "2026-04-08",
          "equity": 98.41
        },
        {
          "date": "2026-04-09",
          "equity": 97.17
        },
        {
          "date": "2026-04-10",
          "equity": 97.99
        },
        {
          "date": "2026-04-13",
          "equity": 99.27
        },
        {
          "date": "2026-04-14",
          "equity": 98.91
        },
        {
          "date": "2026-04-15",
          "equity": 98.07
        },
        {
          "date": "2026-04-16",
          "equity": 100.43
        },
        {
          "date": "2026-04-17",
          "equity": 99.53
        },
        {
          "date": "2026-04-20",
          "equity": 98.84
        },
        {
          "date": "2026-04-21",
          "equity": 98.39
        },
        {
          "date": "2026-04-22",
          "equity": 97.34
        },
        {
          "date": "2026-04-23",
          "equity": 95.83
        },
        {
          "date": "2026-04-24",
          "equity": 95.83
        },
        {
          "date": "2026-04-27",
          "equity": 95.83
        },
        {
          "date": "2026-04-28",
          "equity": 95.83
        },
        {
          "date": "2026-04-29",
          "equity": 95.83
        },
        {
          "date": "2026-04-30",
          "equity": 95.83
        },
        {
          "date": "2026-05-04",
          "equity": 95.83
        },
        {
          "date": "2026-05-05",
          "equity": 95.83
        },
        {
          "date": "2026-05-06",
          "equity": 95.83
        },
        {
          "date": "2026-05-07",
          "equity": 95.83
        },
        {
          "date": "2026-05-08",
          "equity": 95.83
        },
        {
          "date": "2026-05-11",
          "equity": 95.83
        },
        {
          "date": "2026-05-12",
          "equity": 95.83
        },
        {
          "date": "2026-05-13",
          "equity": 95.83
        },
        {
          "date": "2026-05-14",
          "equity": 95.83
        },
        {
          "date": "2026-05-15",
          "equity": 95.83
        },
        {
          "date": "2026-05-18",
          "equity": 95.83
        },
        {
          "date": "2026-05-19",
          "equity": 95.83
        },
        {
          "date": "2026-05-20",
          "equity": 95.83
        },
        {
          "date": "2026-05-21",
          "equity": 95.83
        },
        {
          "date": "2026-05-22",
          "equity": 95.83
        },
        {
          "date": "2026-05-26",
          "equity": 95.83
        },
        {
          "date": "2026-05-27",
          "equity": 95.83
        },
        {
          "date": "2026-05-28",
          "equity": 95.83
        },
        {
          "date": "2026-05-29",
          "equity": 95.83
        },
        {
          "date": "2026-06-01",
          "equity": 95.83
        },
        {
          "date": "2026-06-02",
          "equity": 95.83
        },
        {
          "date": "2026-06-03",
          "equity": 95.83
        },
        {
          "date": "2026-06-04",
          "equity": 95.83
        },
        {
          "date": "2026-06-05",
          "equity": 95.83
        },
        {
          "date": "2026-06-08",
          "equity": 95.83
        },
        {
          "date": "2026-06-09",
          "equity": 95.83
        },
        {
          "date": "2026-06-10",
          "equity": 95.83
        },
        {
          "date": "2026-06-11",
          "equity": 95.83
        },
        {
          "date": "2026-06-12",
          "equity": 95.83
        },
        {
          "date": "2026-06-15",
          "equity": 95.83
        },
        {
          "date": "2026-06-16",
          "equity": 95.83
        },
        {
          "date": "2026-06-17",
          "equity": 95.83
        },
        {
          "date": "2026-06-18",
          "equity": 95.83
        },
        {
          "date": "2026-06-22",
          "equity": 95.83
        },
        {
          "date": "2026-06-23",
          "equity": 95.83
        },
        {
          "date": "2026-06-24",
          "equity": 95.83
        },
        {
          "date": "2026-06-25",
          "equity": 95.83
        },
        {
          "date": "2026-06-26",
          "equity": 95.83
        },
        {
          "date": "2026-06-29",
          "equity": 95.83
        },
        {
          "date": "2026-06-30",
          "equity": 95.83
        },
        {
          "date": "2026-07-02",
          "equity": 95.83
        },
        {
          "date": "2026-07-03",
          "equity": 95.83
        },
        {
          "date": "2026-07-06",
          "equity": 95.83
        },
        {
          "date": "2026-07-06",
          "equity": 95.83
        }
      ]
    }
  ],
  "monthly_heatmap": [
    {
      "stock": "中芯国际(A)",
      "year": 2025,
      "month": 10,
      "return": 0.0
    },
    {
      "stock": "中芯国际(A)",
      "year": 2025,
      "month": 11,
      "return": 0.0
    },
    {
      "stock": "中芯国际(A)",
      "year": 2025,
      "month": 12,
      "return": 0.0009
    },
    {
      "stock": "中芯国际(A)",
      "year": 2026,
      "month": 1,
      "return": -0.0298
    },
    {
      "stock": "中芯国际(A)",
      "year": 2026,
      "month": 2,
      "return": 0.0
    },
    {
      "stock": "中芯国际(A)",
      "year": 2026,
      "month": 3,
      "return": 0.0
    },
    {
      "stock": "中芯国际(A)",
      "year": 2026,
      "month": 4,
      "return": 0.0439
    },
    {
      "stock": "中芯国际(A)",
      "year": 2026,
      "month": 5,
      "return": -0.0654
    },
    {
      "stock": "中芯国际(A)",
      "year": 2026,
      "month": 6,
      "return": -0.0017
    },
    {
      "stock": "中芯国际(A)",
      "year": 2026,
      "month": 7,
      "return": -0.0125
    },
    {
      "stock": "比亚迪(A)",
      "year": 2025,
      "month": 9,
      "return": 0.0
    },
    {
      "stock": "比亚迪(A)",
      "year": 2025,
      "month": 10,
      "return": 0.0
    },
    {
      "stock": "比亚迪(A)",
      "year": 2025,
      "month": 11,
      "return": 0.0
    },
    {
      "stock": "比亚迪(A)",
      "year": 2025,
      "month": 12,
      "return": -0.015
    },
    {
      "stock": "比亚迪(A)",
      "year": 2026,
      "month": 1,
      "return": -0.0071
    },
    {
      "stock": "比亚迪(A)",
      "year": 2026,
      "month": 2,
      "return": 0.0
    },
    {
      "stock": "比亚迪(A)",
      "year": 2026,
      "month": 3,
      "return": -0.0044
    },
    {
      "stock": "比亚迪(A)",
      "year": 2026,
      "month": 4,
      "return": -0.0017
    },
    {
      "stock": "比亚迪(A)",
      "year": 2026,
      "month": 5,
      "return": 0.0
    },
    {
      "stock": "比亚迪(A)",
      "year": 2026,
      "month": 6,
      "return": 0.0
    },
    {
      "stock": "比亚迪(A)",
      "year": 2026,
      "month": 7,
      "return": 0.0
    },
    {
      "stock": "兆易创新",
      "year": 2025,
      "month": 9,
      "return": -0.0143
    },
    {
      "stock": "兆易创新",
      "year": 2025,
      "month": 10,
      "return": -0.0656
    },
    {
      "stock": "兆易创新",
      "year": 2025,
      "month": 11,
      "return": 0.0
    },
    {
      "stock": "兆易创新",
      "year": 2025,
      "month": 12,
      "return": 0.0
    },
    {
      "stock": "兆易创新",
      "year": 2026,
      "month": 1,
      "return": 0.0792
    },
    {
      "stock": "兆易创新",
      "year": 2026,
      "month": 2,
      "return": -0.03
    },
    {
      "stock": "兆易创新",
      "year": 2026,
      "month": 3,
      "return": 0.0
    },
    {
      "stock": "兆易创新",
      "year": 2026,
      "month": 4,
      "return": 0.0
    },
    {
      "stock": "兆易创新",
      "year": 2026,
      "month": 5,
      "return": 0.136
    },
    {
      "stock": "兆易创新",
      "year": 2026,
      "month": 6,
      "return": 0.4623
    },
    {
      "stock": "兆易创新",
      "year": 2026,
      "month": 7,
      "return": -0.1116
    },
    {
      "stock": "中芯国际(H)",
      "year": 2025,
      "month": 9,
      "return": 0.0085
    },
    {
      "stock": "中芯国际(H)",
      "year": 2025,
      "month": 10,
      "return": -0.058
    },
    {
      "stock": "中芯国际(H)",
      "year": 2025,
      "month": 11,
      "return": 0.0
    },
    {
      "stock": "中芯国际(H)",
      "year": 2025,
      "month": 12,
      "return": 0.0
    },
    {
      "stock": "中芯国际(H)",
      "year": 2026,
      "month": 1,
      "return": -0.0068
    },
    {
      "stock": "中芯国际(H)",
      "year": 2026,
      "month": 2,
      "return": 0.0
    },
    {
      "stock": "中芯国际(H)",
      "year": 2026,
      "month": 3,
      "return": 0.0
    },
    {
      "stock": "中芯国际(H)",
      "year": 2026,
      "month": 4,
      "return": 0.0
    },
    {
      "stock": "中芯国际(H)",
      "year": 2026,
      "month": 5,
      "return": -0.0382
    },
    {
      "stock": "中芯国际(H)",
      "year": 2026,
      "month": 6,
      "return": 0.0
    },
    {
      "stock": "中芯国际(H)",
      "year": 2026,
      "month": 7,
      "return": 0.0
    },
    {
      "stock": "比亚迪(H)",
      "year": 2025,
      "month": 9,
      "return": 0.0
    },
    {
      "stock": "比亚迪(H)",
      "year": 2025,
      "month": 10,
      "return": 0.0
    },
    {
      "stock": "比亚迪(H)",
      "year": 2025,
      "month": 11,
      "return": 0.0
    },
    {
      "stock": "比亚迪(H)",
      "year": 2025,
      "month": 12,
      "return": 0.0
    },
    {
      "stock": "比亚迪(H)",
      "year": 2026,
      "month": 1,
      "return": -0.0196
    },
    {
      "stock": "比亚迪(H)",
      "year": 2026,
      "month": 2,
      "return": 0.0
    },
    {
      "stock": "比亚迪(H)",
      "year": 2026,
      "month": 3,
      "return": 0.0013
    },
    {
      "stock": "比亚迪(H)",
      "year": 2026,
      "month": 4,
      "return": -0.021
    },
    {
      "stock": "比亚迪(H)",
      "year": 2026,
      "month": 5,
      "return": 0.0
    },
    {
      "stock": "比亚迪(H)",
      "year": 2026,
      "month": 6,
      "return": 0.0
    },
    {
      "stock": "比亚迪(H)",
      "year": 2026,
      "month": 7,
      "return": 0.0
    }
  ],
  "features": [
    {
      "name": "中芯国际(A)",
      "total_return": -0.0229,
      "max_drawdown": -0.1097,
      "group": "semiconductor",
      "avg_hold_days": 14.2,
      "total_trades": 6,
      "annual_return": -0.0317,
      "sharpe": -0.19
    },
    {
      "name": "比亚迪(A)",
      "total_return": -0.0403,
      "max_drawdown": -0.0403,
      "group": "nev",
      "avg_hold_days": 13.0,
      "total_trades": 2,
      "annual_return": -0.0539,
      "sharpe": -1.64
    },
    {
      "name": "兆易创新",
      "total_return": 0.3116,
      "max_drawdown": -0.1654,
      "group": "semiconductor",
      "avg_hold_days": 20.2,
      "total_trades": 5,
      "annual_return": 0.4412,
      "sharpe": 1.27
    },
    {
      "name": "中芯国际(H)",
      "total_return": -0.0416,
      "max_drawdown": -0.1267,
      "group": "semiconductor",
      "avg_hold_days": 14.8,
      "total_trades": 5,
      "annual_return": -0.0548,
      "sharpe": -0.56
    },
    {
      "name": "比亚迪(H)",
      "total_return": -0.0417,
      "max_drawdown": -0.0458,
      "group": "nev",
      "avg_hold_days": 19.0,
      "total_trades": 2,
      "annual_return": -0.0549,
      "sharpe": -1.37
    }
  ]
}